setup.cfg
setup.py
yijing/__init__.py
yijing/iching.py
yijing.egg-info/PKG-INFO
yijing.egg-info/SOURCES.txt
yijing.egg-info/dependency_links.txt
yijing.egg-info/not-zip-safe
yijing.egg-info/top_level.txt