Metadata-Version: 1.0
Name: yijing
Version: 0.1
Summary: I Ching predictor
Home-page: http://github.com/brez/yijing
Author: de la brez
Author-email: UNKNOWN
License: MIT
Platform: UNKNOWN
